
[
  {
    "id": "rnartist",
    "name": "RNArtist",
    "company": "Fabrise Jossinet (University of Strasbourg)",
    "url": "https://github.com/fjossinet/RNArtist",
    "domain": "Research",
    "summary": "An editor for creating 2D RNA structures.",
    "videoIds": []
  },
  {
    "id": "presentationbuilder",
    "name": "Presentation Builder",
    "company": "Sideline Sports",
    "url": "https://xps.sidelinesports.com",
    "domain": "Sports",
    "summary": "An editor for composing coaching videos.",
    "videoIds": []
  },
  {
    "id": "aida",
    "name": "AIDA",
    "company": "Deutsche AIDS Stiftung",
    "url": "",
    "domain": "Office Integration",
    "summary": "Office integration software to support AIDS patients."
  },
  {
    "id": "bisq",
    "name": "bisq",
    "company": "bisq",
    "url": "https://bisq.network",
    "domain": "Cryptocurrencies",
    "summary": "Buy and sell bitcoin privately and securely."
  },
  {
    "id": "debeka",
    "name": "Debeka DVC",
    "company": "Debeka",
    "url": "https://www.debeka.de/index.html",
    "domain": "Insurance",
    "summary": "Insurance coverage check software."
  },
  {
    "id": "ebu",
    "name": "NEOS",
    "company": "European Broadcasting Union",
    "url": "",
    "domain": "Planning & Scheduling",
    "summary": "Radio & TV transmission planning solution.",
    "videos": [
      "RN_Pcu8ssQc"
    ]
  },
  {
    "id": "eizo",
    "name": "CuratOR",
    "company": "EIZO",
    "url": "https://eizo-or.com/en/global/products/or-software/curator-caliop-vm/",
    "domain": "Medical",
    "summary": "Experience the future of operating room technology"
  },
  {
    "id": "emirates",
    "name": "Emirates NCO",
    "company": "Emirates Airlines",
    "url": "",
    "domain": "Logistics",
    "summary": "A resource network optimization solution."
  },
  {
    "id": "equinox",
    "name": "Airbus Equinox",
    "company": "Airbus",
    "url": "",
    "domain": "Engineering",
    "summary": "Simulation and analysis software."
  },
  {
    "id": "hrc",
    "name": "HRC-Matic",
    "company": "AISO",
    "url": "",
    "domain": "Business Registry",
    "summary": "Business registry software."
  },
  {
    "id": "justiz",
    "name": "GeFa",
    "company": "BestSolution",
    "url": "https://gefa-justiz.de",
    "domain": "Justice",
    "summary": "Management software for justice processes."
  },
  {
    "id": "lynden",
    "name": "Lynden",
    "company": "Lynden",
    "url": "",
    "domain": "Logistics",
    "summary": "Resource scheduling application."
  },
  {
    "id": "meyersound",
    "name": "MAPP XT",
    "company": "Meyer Sound",
    "url": "https://meyersound.com/product/mapp-xt/",
    "domain": "Music",
    "summary": "Audio coverage analysis tool."
  },
  {
    "id": "mint",
    "name": "MINT TRMS",
    "company": "Mint Media",
    "url": "https://mintsoftwaresystems.com",
    "domain": "Aviation",
    "summary": "Training and resource management for airlines.",
    "videoIds": [
      "d-oxGpUkFe4"
    ]
  },
  {
    "id": "monastery",
    "name": "Monastery Disentis",
    "company": "Monastery Disentis",
    "url": "https://apps.apple.com/ch/app/kloster-disentis/id1208078669?l=en",
    "domain": "Tourism",
    "summary": "Tourist guide for mobile devices.",
    "videoIds": [
      "67RonidGgEA"
    ]
  },
  {
    "id": "mosaic",
    "name": "Mosaic",
    "company": "Airbus",
    "url": "",
    "domain": "Resource Scheduling",
    "summary": "Satellite ground tracking software."
  },
  {
    "id": "mpmedia",
    "name": "mpGAFOR",
    "company": "mpMedia",
    "url": "",
    "domain": "Aviation",
    "summary": "Flight planning software."
  },
  {
    "id": "deepspace",
    "name": "Deep Space Trajectory Explorer",
    "company": "NASA",
    "url": "https://ai-solutions.com/dste/",
    "domain": "Research",
    "summary": "Explore possible orbits in space.",
    "videoIds": [
      "MotQ1PC1xT8"
    ]
  },
  {
    "id": "projektpro",
    "name": "ProjektPro",
    "company": "ProjektPro",
    "url": "https://www.projektpro.com",
    "domain": "Architecture",
    "summary": "Office software for architects."
  },
  {
    "id": "psi",
    "name": "PSI ASM",
    "company": "PSI",
    "url": "https://www.psi.pl/en/products-services/production/",
    "domain": "Manufacturing Execution Systems",
    "summary": "Production process tracking."
  },
  {
    "id": "eteoboard",
    "name": "eteoBoard",
    "company": "Saxonia Systems / ZEISS",
    "url": "https://marketplace.atlassian.com/apps/1220715/eteoboard-the-more-agile-agile-board?hosting=server&tab=overview",
    "domain": "Agile Project Management",
    "summary": "Agile board for teams.",
    "videoIds": [
      "TlHjX2uZzxA"
    ]
  },
  {
    "id": "senapt",
    "name": "Senapt EaaS",
    "company": "Senapt Inc.",
    "url": "https://www.senapt.co.uk",
    "domain": "CRM",
    "summary": "CRM system for energy suppliers."
  },
  {
    "id": "skedpal",
    "name": "SkedPal",
    "company": "SkepPad",
    "url": "https://www.skedpal.com",
    "domain": "Scheduling",
    "summary": "Smart calendar to get things done."
  },
  {
    "id": "sophia",
    "name": "Sophia DDM",
    "company": "Sophia Genetics",
    "url": "https://www.sophiagenetics.com",
    "domain": "Medical",
    "summary": "Insights from digital health data.",
    "videoIds": [
      "mJEKQHgBvug"
    ]
  },
  {
    "id": "threesixty",
    "name": "360T",
    "company": "360T",
    "url": "https://www.360t.com/products/360tgtx-suite/",
    "domain": "Trading",
    "summary": "Trading solution for FX market participants."
  },
  {
    "id": "vesseleditor",
    "name": "Vessel Editor",
    "company": "Contship Italia Group",
    "url": "https://karakun.com/en/how-do-you-visualize-data/",
    "domain": "Logistics",
    "summary": "Optimize utilization of vessel cargo space."
  },
  {
    "id": "witt",
    "name": "Call Center App",
    "company": "Witt Weiden (OTTO)",
    "url": "",
    "domain": "CRM",
    "summary": "Modern call center application."
  },
  {
    "id": "woanna",
    "name": "Woanna",
    "company": "Woanna",
    "url": "",
    "domain": "Team Management",
    "summary": "Team collaboration and scheduling software."
  },
  {
    "id": "yardeditor",
    "name": "Yard Editor",
    "company": "Contship Italia Group",
    "url": "https://karakun.com/en/how-do-you-visualize-data/",
    "domain": "",
    "summary": "Optimize utilization of container yards."
  },
  {
    "id": "zeiss",
    "name": "FORUM",
    "company": "Carl Zeiss Meditec AG",
    "url": "https://www.zeiss.ch/meditec/produkte/ophthalmologie/ophthalmology-pacs-forum.html",
    "domain": "Medical",
    "summary": "Scalable software for ophthalmology"
  },
  {
    "id": "streampi",
    "name": "StreamPi",
    "company": "",
    "url": "stream-pi.com",
    "domain": "MacroPads",
    "summary": "An open source, cross-platform, programmable, modular Macropad software."
  }
]